setup.py
flyfingers/__init__.py
flyfingers/cli.py
flyfingers.egg-info/PKG-INFO
flyfingers.egg-info/SOURCES.txt
flyfingers.egg-info/dependency_links.txt
flyfingers.egg-info/top_level.txt
scripts/flyfingers