Metadata-Version: 1.1
Name: flyfingers
Version: 0.1
Summary: Learn to type 10 fingers
Home-page: UNKNOWN
Author: Thanh Nguyen Tuong
Author-email: ngtthanh1010@gmail.com
License: MIT
Platform: UNKNOWN
Classifier: Environment :: Console
Classifier: Topic :: Terminals :: Terminal Emulators/X Terminals
